sphinx_version_ref/__init__.py
sphinx_version_ref-0.1.0.dist-info/LICENSE
sphinx_version_ref-0.1.0.dist-info/METADATA
sphinx_version_ref-0.1.0.dist-info/WHEEL
sphinx_version_ref-0.1.0.dist-info/top_level.txt
sphinx_version_ref-0.1.0.dist-info/RECORD
