Metadata-Version: 2.1
Name: sphinx-version-ref
Version: 0.1.0
Summary: Sphinx extension to substitute version in references.
Home-page: http://sphinx-version-ref.readthedocs.io/
Author: M.J.W. Snippe
Author-email: maxsnippe@gmail.com
License: MIT
Project-URL: Issue tracker, https://github.com/max-sn/sphinx_version_ref/issues
Project-URL: Documentation, http://sphinx-version-ref.readthedocs.io/
Project-URL: Repository, https://github.com/max-sn/sphinx_version_ref/
Platform: any
Classifier: Development Status :: 4 - Beta
Classifier: Environment :: Console
Classifier: Environment :: Web Environment
Classifier: Intended Audience :: Developers
Classifier: License :: OSI Approved :: MIT License
Classifier: Operating System :: OS Independent
Classifier: Programming Language :: Python
Classifier: Topic :: Documentation
Classifier: Topic :: Utilities
Requires-Dist: Sphinx (>=1.3)
Requires-Dist: setuptools (>=20.7)
